jmespath/__init__.py
jmespath/ast.py
jmespath/compat.py
jmespath/exceptions.py
jmespath/functions.py
jmespath/lexer.py
jmespath/parser.py
jmespath/visitor.py
jmespath-0.9.2.data/scripts/jp
jmespath-0.9.2.data/scripts/jp.py
jmespath-0.9.2.dist-info/DESCRIPTION.rst
jmespath-0.9.2.dist-info/METADATA
jmespath-0.9.2.dist-info/metadata.json
jmespath-0.9.2.dist-info/RECORD
jmespath-0.9.2.dist-info/top_level.txt
jmespath-0.9.2.dist-info/WHEEL
