Metadata-Version: 1.1
Name: jmespath
Version: 0.9.2
Summary: JSON Matching Expressions
Home-page: https://github.com/jmespath/jmespath.py
Author: James Saryerwinnie
Author-email: js@jamesls.com
License: MIT
Platform: UNKNOWN
Classifier: Development Status :: 5 - Production/Stable
Classifier: Intended Audience :: Developers
Classifier: Natural Language :: English
Classifier: License :: OSI Approved :: MIT License
Classifier: Programming Language :: Python
Classifier: Programming Language :: Python :: 2.6
Classifier: Programming Language :: Python :: 2.7
Classifier: Programming Language :: Python :: 3
Classifier: Programming Language :: Python :: 3.3
Classifier: Programming Language :: Python :: 3.4
